facebook_video_downloader/__init__.py
facebook_video_downloader/config/__init__.py
facebook_video_downloader/config/config.py
facebook_video_downloader/demo/__init__.py
facebook_video_downloader/demo/demo.py
facebook_video_downloader/house_keeping/__init__.py
facebook_video_downloader/house_keeping/house_keeper.py
facebook_video_downloader/model/__init__.py
facebook_video_downloader/model/video.py
facebook_video_downloader/regex/__init__.py
facebook_video_downloader/regex/fb_downloader_regex.py
facebook_video_downloader/video_downloader/__init__.py
facebook_video_downloader/video_downloader/video_downloader.py
fb_video_downloader_renanrgs-0.0.11.dist-info/METADATA
fb_video_downloader_renanrgs-0.0.11.dist-info/WHEEL
fb_video_downloader_renanrgs-0.0.11.dist-info/top_level.txt
fb_video_downloader_renanrgs-0.0.11.dist-info/RECORD
